azure/ai/resources/__init__.py
azure/ai/resources/_project_scope.py
azure/ai/resources/_user_agent.py
azure/ai/resources/_version.py
azure/ai/resources/py.typed
azure/ai/resources/_index/__init__.py
azure/ai/resources/_index/_docstore.py
azure/ai/resources/_index/_mlindex.py
azure/ai/resources/_index/_models.py
azure/ai/resources/_index/_dataindex/__init__.py
azure/ai/resources/_index/_dataindex/_schema/__init__.py
azure/ai/resources/_index/_dataindex/_schema/_data_index/__init__.py
azure/ai/resources/_index/_dataindex/_schema/_data_index/data_index.py
azure/ai/resources/_index/_dataindex/constants/__init__.py
azure/ai/resources/_index/_dataindex/constants/_component.py
azure/ai/resources/_index/_dataindex/data_index/__init__.py
azure/ai/resources/_index/_dataindex/data_index/models.py
azure/ai/resources/_index/_dataindex/dsl/__init__.py
azure/ai/resources/_index/_dataindex/dsl/_pipeline_decorator.py
azure/ai/resources/_index/_dataindex/entities/__init__.py
azure/ai/resources/_index/_dataindex/entities/data_index.py
azure/ai/resources/_index/_dataindex/entities/_assets/__init__.py
azure/ai/resources/_index/_dataindex/entities/_assets/_artifacts/__init__.py
azure/ai/resources/_index/_dataindex/entities/_assets/_artifacts/data.py
azure/ai/resources/_index/_dataindex/entities/_builders/__init__.py
azure/ai/resources/_index/_dataindex/entities/_builders/data_index_func.py
azure/ai/resources/_index/_dataindex/operations/__init__.py
azure/ai/resources/_index/_dataindex/operations/_data_operations.py
azure/ai/resources/_index/_documents/__init__.py
azure/ai/resources/_index/_documents/document.py
azure/ai/resources/_index/_embeddings/__init__.py
azure/ai/resources/_index/_embeddings/openai.py
azure/ai/resources/_index/_indexes/__init__.py
azure/ai/resources/_index/_indexes/azure_search.py
azure/ai/resources/_index/_indexes/faiss.py
azure/ai/resources/_index/_langchain/__init__.py
azure/ai/resources/_index/_langchain/acs.py
azure/ai/resources/_index/_langchain/docstore.py
azure_ai_resources-1.0.0b9.dist-info/METADATA
azure_ai_resources-1.0.0b9.dist-info/WHEEL
azure_ai_resources-1.0.0b9.dist-info/top_level.txt
azure_ai_resources-1.0.0b9.dist-info/RECORD
