Metadata-Version: 2.1
Name: azure-ai-resources
Version: 1.0.0b9
Summary: Microsoft Azure Azure AI control plane SDK Client Library for Python
Home-page: https://github.com/Azure/azure-sdk-for-python
Author: Microsoft Corporation
Author-email: azuresdkengsysadmins@microsoft.com
License: MIT License
Project-URL: Bug Reports, https://github.com/Azure/azure-sdk-for-python/issues
Project-URL: Source, https://github.com/Azure/azure-sdk-for-python
Keywords: azure,azuresdk,azure sdk
Classifier: Development Status :: 7 - Inactive
Classifier: Programming Language :: Python
Classifier: Programming Language :: Python :: 3
Classifier: Programming Language :: Python :: 3 :: Only
Classifier: Programming Language :: Python :: 3.8
Classifier: Programming Language :: Python :: 3.9
Classifier: Programming Language :: Python :: 3.10
Classifier: Programming Language :: Python :: 3.11
Classifier: Programming Language :: Python :: 3.12
Classifier: License :: OSI Approved :: MIT License
Requires-Python: <4.0,>=3.8
Requires-Dist: azure-ai-ml>=1.14.0
Requires-Dist: mlflow-skinny<3
Requires-Dist: opencensus-ext-logging<=0.1.1
Requires-Dist: azure-mgmt-resource<23.0.0,>=22.0.0
